evd_sdk_lotr/__init__.py
evd_sdk_lotr/books.py
evd_sdk_lotr/chapters.py
evd_sdk_lotr/characters.py
evd_sdk_lotr/movies.py
evd_sdk_lotr/quotes.py
evd_sdk_lotr/settings.py
evd_sdk_lotr-0.0.9.dist-info/LICENSE
evd_sdk_lotr-0.0.9.dist-info/METADATA
evd_sdk_lotr-0.0.9.dist-info/WHEEL
evd_sdk_lotr-0.0.9.dist-info/top_level.txt
evd_sdk_lotr-0.0.9.dist-info/RECORD
