Metadata-Version: 2.1
Name: evd-sdk-lotr
Version: 0.0.9
Summary: A LOTR API SDK
Home-page: https://gitlab.com/ericadippold/erica-dippold-sdk
Author: Erica
Author-email: ericavdippold@gmail.com
Project-URL: Bug Tracker, https://gitlab.com/ericadippold/erica-dippold-sdk
Classifier: Programming Language :: Python :: 3
Classifier: License :: OSI Approved :: MIT License
Classifier: Operating System :: OS Independent
Requires-Python: >=3.6
License-File: LICENSE
